nexa_stt/__init__.py
nexa_package-0.1.dist-info/METADATA
nexa_package-0.1.dist-info/WHEEL
nexa_package-0.1.dist-info/top_level.txt
nexa_package-0.1.dist-info/RECORD
