Metadata-Version: 2.4
Name: nexa_package
Version: 0.1
Summary: A package for speech to text conversion using selenium
Author: Harshit Verma
Author-email: harshitvermami4i@gmail.com
Requires-Dist: selenium
Requires-Dist: webdriver-manager
Dynamic: author
Dynamic: author-email
Dynamic: requires-dist
Dynamic: summary
